Workbook

Sheet Assumptions
A1: Corporate Membership — Cost Assumptions
A2: Edit the yellow cells with your real costs. Every other tab calculates off these — nothing downstream is hardcoded.
A4: Assumption | B4: Value | C4: Notes
A5: Attendant loaded labor rate ($/hr) | B5: 30 | C5: Fully loaded incl. payroll tax/benefits. Source: placeholder — replace with your real rate.
A6: Avg on-site hours — attended activation | B6: 5 | C6: Setup + event + breakdown + travel buffer for a staffed experience.
A7: Avg on-site hours — non-attended / drop-off / Video Wall | B7: 2.5 | C7: Delivery, setup, and pickup only — no attendant during the event.
A8: Flat travel/mileage cost per activation | B8: 40 | C8: Per site visit. Placeholder — replace with your real avg. mileage cost for Atlanta metro.
A9: Equipment wear & amortization per activation | B9: 35 | C9: Placeholder allocation for equipment depreciation/repair per use.
A10: Insurance & overhead allocation per activation | B10: 20 | C10: Placeholder — allocate your liability insurance + general overhead per booking.
A11: Utilization rate (% of paying members who activate in a given month) | B11: 0.7 | C11: Key lever: membership only costs you money in months the member actually uses it.
A13: Recommended Structure — Annual Usage Caps
A14: Assumption | B14: Value | C14: Notes
A15: Tier 1 — activations per year (quarterly cap) | B15: 4 | C15: Recommended: cap at 1 per quarter instead of 1 per month.
A16: Tier 2 — activations per year (annual cap) | B16: 1 | C16: Recommended: cap at 1 full multi-experience build-out per year. Additional build-outs billed separately (see Recommended Tier 2 tab).

Sheet Cost Per Experience
A1: Estimated Variable Cost Per Activation, By Experience
A2: Total Variable Cost and Cost Excl. Travel are formulas pulling from the Assumptions tab. Non-attended rows are grouped at the bottom (rows 15-20) so the Tier 2 tab can reference them as a contiguous range.
A4: Experience | B4: Tier | C4: A La Carte Price | D4: Attended? | E4: On-Site Hours | F4: Attendant Labor Cost | G4: Travel Cost | H4: Wear Cost | I4: Overhead Cost | J4: Total Variable Cost | K4: Cost Excl. Travel | L4: Margin $ (vs a la carte) | M4: Margin %
A5: Vintage Photo Booth | B5: Essential | C5: 750 | D5: Y | E5: =IF(D5="Y",Assumptions!$B$6,Assumptions!$B$7) | F5: =E5*Assumptions!$B$5 | G5: =Assumptions!$B$8 | H5: =Assumptions!$B$9 | I5: =Assumptions!$B$10 | J5: =F5+G5+H5+I5 | K5: =F5+H5+I5 | L5: =C5-J5 | M5: =L5/C5
A6: Vintage Photo Booth | B6: Signature | C6: 850 | D6: Y | E6: =IF(D6="Y",Assumptions!$B$6,Assumptions!$B$7) | F6: =E6*Assumptions!$B$5 | G6: =Assumptions!$B$8 | H6: =Assumptions!$B$9 | I6: =Assumptions!$B$10 | J6: =F6+G6+H6+I6 | K6: =F6+H6+I6 | L6: =C6-J6 | M6: =L6/C6
A7: Vintage Photo Booth | B7: Black Tie | C7: 950 | D7: Y | E7: =IF(D7="Y",Assumptions!$B$6,Assumptions!$B$7) | F7: =E7*Assumptions!$B$5 | G7: =Assumptions!$B$8 | H7: =Assumptions!$B$9 | I7: =Assumptions!$B$10 | J7: =F7+G7+H7+I7 | K7: =F7+H7+I7 | L7: =C7-J7 | M7: =L7/C7
A8: Mirror Booth | B8: Essential | C8: 750 | D8: Y | E8: =IF(D8="Y",Assumptions!$B$6,Assumptions!$B$7) | F8: =E8*Assumptions!$B$5 | G8: =Assumptions!$B$8 | H8: =Assumptions!$B$9 | I8: =Assumptions!$B$10 | J8: =F8+G8+H8+I8 | K8: =F8+H8+I8 | L8: =C8-J8 | M8: =L8/C8
A9: Mirror Booth | B9: Signature | C9: 850 | D9: Y | E9: =IF(D9="Y",Assumptions!$B$6,Assumptions!$B$7) | F9: =E9*Assumptions!$B$5 | G9: =Assumptions!$B$8 | H9: =Assumptions!$B$9 | I9: =Assumptions!$B$10 | J9: =F9+G9+H9+I9 | K9: =F9+H9+I9 | L9: =C9-J9 | M9: =L9/C9
A10: Mirror Booth | B10: Black Tie | C10: 950 | D10: Y | E10: =IF(D10="Y",Assumptions!$B$6,Assumptions!$B$7) | F10: =E10*Assumptions!$B$5 | G10: =Assumptions!$B$8 | H10: =Assumptions!$B$9 | I10: =Assumptions!$B$10 | J10: =F10+G10+H10+I10 | K10: =F10+H10+I10 | L10: =C10-J10 | M10: =L10/C10
A11: British Phone Booth | B11: Signature | C11: 950 | D11: Y | E11: =IF(D11="Y",Assumptions!$B$6,Assumptions!$B$7) | F11: =E11*Assumptions!$B$5 | G11: =Assumptions!$B$8 | H11: =Assumptions!$B$9 | I11: =Assumptions!$B$10 | J11: =F11+G11+H11+I11 | K11: =F11+H11+I11 | L11: =C11-J11 | M11: =L11/C11
A12: British Phone Booth | B12: Black Tie | C12: 1150 | D12: Y | E12: =IF(D12="Y",Assumptions!$B$6,Assumptions!$B$7) | F12: =E12*Assumptions!$B$5 | G12: =Assumptions!$B$8 | H12: =Assumptions!$B$9 | I12: =Assumptions!$B$10 | J12: =F12+G12+H12+I12 | K12: =F12+H12+I12 | L12: =C12-J12 | M12: =L12/C12
A13: 360 Video Booth | B13: Essential | C13: 950 | D13: Y | E13: =IF(D13="Y",Assumptions!$B$6,Assumptions!$B$7) | F13: =E13*Assumptions!$B$5 | G13: =Assumptions!$B$8 | H13: =Assumptions!$B$9 | I13: =Assumptions!$B$10 | J13: =F13+G13+H13+I13 | K13: =F13+H13+I13 | L13: =C13-J13 | M13: =L13/C13
A14: 360 Video Booth | B14: Signature | C14: 1150 | D14: Y | E14: =IF(D14="Y",Assumptions!$B$6,Assumptions!$B$7) | F14: =E14*Assumptions!$B$5 | G14: =Assumptions!$B$8 | H14: =Assumptions!$B$9 | I14: =Assumptions!$B$10 | J14: =F14+G14+H14+I14 | K14: =F14+H14+I14 | L14: =C14-J14 | M14: =L14/C14
A15: 360 Video Booth | B15: Black Tie | C15: 1350 | D15: Y | E15: =IF(D15="Y",Assumptions!$B$6,Assumptions!$B$7) | F15: =E15*Assumptions!$B$5 | G15: =Assumptions!$B$8 | H15: =Assumptions!$B$9 | I15: =Assumptions!$B$10 | J15: =F15+G15+H15+I15 | K15: =F15+H15+I15 | L15: =C15-J15 | M15: =L15/C15
A16: Classic Photo Booth (Drop-Off) | B16: Essential | C16: 499 | D16: N | E16: =IF(D16="Y",Assumptions!$B$6,Assumptions!$B$7) | F16: =E16*Assumptions!$B$5 | G16: =Assumptions!$B$8 | H16: =Assumptions!$B$9 | I16: =Assumptions!$B$10 | J16: =F16+G16+H16+I16 | K16: =F16+H16+I16 | L16: =C16-J16 | M16: =L16/C16
... A21: Video Wall | B21: 2 Screens | C21: 1000 | D21: N | E21: =IF(D21="Y",Assumptions!$B$6,Assumptions!$B$7) | F21: =E21*Assumptions!$B$5 | G21: =Assumptions!$B$8 | H21: =Assumptions!$B$9 | I21: =Assumptions!$B$10 | J21: =F21+G21+H21+I21 | K21: =F21+H21+I21 | L21: =C21-J21 | M21: =L21/C21
A23: Attended-experience block: rows 5-15. Non-attended block: rows 16-21. Used by the Tier 2 tab's LARGE/SMALL formulas.

Sheet Tier 1 Profitability
A1: Tier 1 — $199/mo, One Activation of Any Single Experience
A3: Monthly Membership Price | B3: 199 | C3: Edit this to test other price points.
A5: Scenario | B5: Activation Cost | C5: Margin $ (per activation, if used) | D5: Margin %
A6: Best case — member picks cheapest eligible experience | B6: =MIN('Cost Per Experience'!J5:J21) | C6: =$B$3-B6 | D6: =C6/$B$3
A7: Worst case — member picks most expensive eligible experience | B7: =MAX('Cost Per Experience'!J5:J21) | C7: =$B$3-B7 | D7: =C7/$B$3
A9: Expected Monthly Margin (accounts for utilization — cost only hits in months the member activates)
A10: Scenario | B10: Expected Monthly Margin
A11: Best case, at assumed utilization | B11: =$B$3-(B6*Assumptions!$B$11)
A12: Worst case, at assumed utilization | B12: =$B$3-(B7*Assumptions!$B$11)
A14: Reality check: 'any experience' with no price ceiling means a member can request your $1,350 360 Video Black Tie booth every month for $199 — that scenario alone loses money on almost every activation. See Breakeven & Sensitivity for the utilization rate needed to stay profitable.

Sheet Tier 2 Profitability
A1: Tier 2 — $275/mo, One Event Combining Up To 3 Experiences (Same Date)
A3: Monthly Membership Price | B3: 275 | C3: Edit this to test other price points.
A5: Scenario | B5: Combined Activation Cost (3 experiences, 1 shared travel fee) | C5: Margin $ (per event, if used) | D5: Margin %
A6: Worst case — 3 most expensive attended experiences combined (e.g. full premium build-out) | B6: =LARGE('Cost Per Experience'!K5:K15,1)+LARGE('Cost Per Experience'!K5:K15,2)+LARGE('Cost Per Experience'!K5:K15,3)+Assumptions!$B$8 | C6: =$B$3-B6 | D6: =C6/$B$3
A7: Floor case — 3 cheapest non-attended experiences combined (Classic/Video Wall only) | B7: =SMALL('Cost Per Experience'!K16:K21,1)+SMALL('Cost Per Experience'!K16:K21,2)+SMALL('Cost Per Experience'!K16:K21,3)+Assumptions!$B$8 | C7: =$B$3-B7 | D7: =C7/$B$3
A9: Expected Monthly Margin (accounts for utilization)
A10: Scenario | B10: Expected Monthly Margin
A11: Worst case, at assumed utilization | B11: =$B$3-(B6*Assumptions!$B$11)
A12: Floor case, at assumed utilization | B12: =$B$3-(B7*Assumptions!$B$11)
A14: Reality check: combining 3 attended experiences (e.g. Mirror Booth + 360 Video + British Phone Booth) at one event realistically costs several hundred dollars in labor alone — well above $275. This tier only works if (a) it's restricted to lighter/non-attended combos, (b) it's priced much higher to match your existing $2,000+ full-build-out corporate rate, or (c) utilization is low enough that the fixed monthly fee outruns the occasional activation cost. See Breakeven & Sensitivity.

Sheet Breakeven & Sensitivity
A1: Monthly Margin Per Member, By Utilization Rate
A2: Utilization = % of paying members who actually activate their membership in a given month. Revenue is collected every month regardless; cost only hits in months they use it.
A4: Scenario | B4: 0.2 | C4: 0.3 | D4: 0.4 | E4: 0.5 | F4: 0.6 | G4: 0.7 | H4: 0.8 | I4: 0.9 | J4: 1
A5: Tier 1 — Worst Case (priciest experience) | B5: ='Tier 1 Profitability'!$B$3-('Tier 1 Profitability'!$B$7*B$4) | C5: ='Tier 1 Profitability'!$B$3-('Tier 1 Profitability'!$B$7*C$4) | D5: ='Tier 1 Profitability'!$B$3-('Tier 1 Profitability'!$B$7*D$4) | E5: ='Tier 1 Profitability'!$B$3-('Tier 1 Profitability'!$B$7*E$4) | F5: ='Tier 1 Profitability'!$B$3-('Tier 1 Profitability'!$B$7*F$4) | G5: ='Tier 1 Profitability'!$B$3-('Tier 1 Profitability'!$B$7*G$4) | H5: ='Tier 1 Profitability'!$B$3-('Tier 1 Profitability'!$B$7*H$4) | I5: ='Tier 1 Profitability'!$B$3-('Tier 1 Profitability'!$B$7*I$4) | J5: ='Tier 1 Profitability'!$B$3-('Tier 1 Profitability'!$B$7*J$4)
A6: Tier 1 — Best Case (cheapest experience) | B6: ='Tier 1 Profitability'!$B$3-('Tier 1 Profitability'!$B$6*B$4) | C6: ='Tier 1 Profitability'!$B$3-('Tier 1 Profitability'!$B$6*C$4) | D6: ='Tier 1 Profitability'!$B$3-('Tier 1 Profitability'!$B$6*D$4) | E6: ='Tier 1 Profitability'!$B$3-('Tier 1 Profitability'!$B$6*E$4) | F6: ='Tier 1 Profitability'!$B$3-('Tier 1 Profitability'!$B$6*F$4) | G6: ='Tier 1 Profitability'!$B$3-('Tier 1 Profitability'!$B$6*G$4) | H6: ='Tier 1 Profitability'!$B$3-('Tier 1 Profitability'!$B$6*H$4) | I6: ='Tier 1 Profitability'!$B$3-('Tier 1 Profitability'!$B$6*I$4) | J6: ='Tier 1 Profitability'!$B$3-('Tier 1 Profitability'!$B$6*J$4)
A7: Tier 2 — Worst Case (3 attended combined) | B7: ='Tier 2 Profitability'!$B$3-('Tier 2 Profitability'!$B$6*B$4) | C7: ='Tier 2 Profitability'!$B$3-('Tier 2 Profitability'!$B$6*C$4) | D7: ='Tier 2 Profitability'!$B$3-('Tier 2 Profitability'!$B$6*D$4) | E7: ='Tier 2 Profitability'!$B$3-('Tier 2 Profitability'!$B$6*E$4) | F7: ='Tier 2 Profitability'!$B$3-('Tier 2 Profitability'!$B$6*F$4) | G7: ='Tier 2 Profitability'!$B$3-('Tier 2 Profitability'!$B$6*G$4) | H7: ='Tier 2 Profitability'!$B$3-('Tier 2 Profitability'!$B$6*H$4) | I7: ='Tier 2 Profitability'!$B$3-('Tier 2 Profitability'!$B$6*I$4) | J7: ='Tier 2 Profitability'!$B$3-('Tier 2 Profitability'!$B$6*J$4)
A8: Tier 2 — Floor Case (3 non-attended combined) | B8: ='Tier 2 Profitability'!$B$3-('Tier 2 Profitability'!$B$7*B$4) | C8: ='Tier 2 Profitability'!$B$3-('Tier 2 Profitability'!$B$7*C$4) | D8: ='Tier 2 Profitability'!$B$3-('Tier 2 Profitability'!$B$7*D$4) | E8: ='Tier 2 Profitability'!$B$3-('Tier 2 Profitability'!$B$7*E$4) | F8: ='Tier 2 Profitability'!$B$3-('Tier 2 Profitability'!$B$7*F$4) | G8: ='Tier 2 Profitability'!$B$3-('Tier 2 Profitability'!$B$7*G$4) | H8: ='Tier 2 Profitability'!$B$3-('Tier 2 Profitability'!$B$7*H$4) | I8: ='Tier 2 Profitability'!$B$3-('Tier 2 Profitability'!$B$7*I$4) | J8: ='Tier 2 Profitability'!$B$3-('Tier 2 Profitability'!$B$7*J$4)
A10: Breakeven Utilization Rate (margin = $0)
A11: Tier 1 — Worst Case | B11: ='Tier 1 Profitability'!$B$3/'Tier 1 Profitability'!$B$7
A12: Tier 1 — Best Case | B12: ='Tier 1 Profitability'!$B$3/'Tier 1 Profitability'!$B$6
A13: Tier 2 — Worst Case | B13: ='Tier 2 Profitability'!$B$3/'Tier 2 Profitability'!$B$6
A14: Tier 2 — Floor Case | B14: ='Tier 2 Profitability'!$B$3/'Tier 2 Profitability'!$B$7
A16: A breakeven rate above 100% means that scenario never breaks even, no matter how rarely the member activates the benefit — the per-use cost simply exceeds the monthly fee. A breakeven rate below your assumed utilization (Assumptions tab, default 70%) means you're losing money on the average member in that scenario today.

Sheet Comparison to One-Off Corporate
A1: Membership Revenue vs. Your Existing One-Off Corporate Pricing
A2: Source: BTB_EmailTemplates_ReactivationAndCorporate.pdf, 'Corporate Holiday Pitch' section (Revenue Potential).
A4: One-Off Corporate Booking Type | B4: Low | C4: High
A5: Base booking | B5: 800 | C5: 1350
A6: With Video Wall add-on | B6: 1400 | C6: 2350
A7: Full corporate build-out | B7: 2000 | C7: 2,000+ (open-ended)
A9: 12-Month Membership Revenue | B9: Amount
A10: Tier 1 ($199/mo x 12) | B10: ='Tier 1 Profitability'!$B$3*12
A11: Tier 2 ($275/mo x 12) | B11: ='Tier 2 Profitability'!$B$3*12
A13: Cannibalization risk: a full year of Tier 2 membership ($3,300) roughly equals just ONE full corporate build-out ($2,000+) plus a base booking. If a corporate client would otherwise have booked 2-3 one-off premium events a year at $1,500-$2,350 each, converting them to a $275/mo membership can significantly cut your revenue per client — unless the membership successfully drives MORE total activations (e.g. monthly team events) than they'd ever have booked a la carte. Model this against your actual corporate client repeat-booking rate before rolling this out broadly.

Sheet Recommended Tier 1 (Annual)
A1: Recommended — Tier 1: $199/mo Billed Monthly, Capped at 1 Activation Per Quarter
A2: Same $199/mo price the member sees. The only change: usage is capped to 4 activations/year (quarterly) instead of unlimited monthly, with an annual commitment.
A4: Monthly Price (as marketed) | B4: ='Tier 1 Profitability'!$B$3
A5: Annual Revenue (12 months, required commitment) | B5: =B4*12
A6: Annual Activation Cap | B6: =Assumptions!$B$15
A8: Scenario | B8: Cost Per Activation | C8: Total Annual Cost (cap x cost) | D8: Annual Margin $ | E8: Annual Margin % | F8: Monthly-Equivalent Margin
A9: Best case — member always picks cheapest eligible experience | B9: =MIN('Cost Per Experience'!J5:J21) | C9: =B9*$B$6 | D9: =$B$5-C9 | E9: =D9/$B$5 | F9: =D9/12
A10: Worst case — member always picks most expensive eligible experience | B10: =MAX('Cost Per Experience'!J5:J21) | C10: =B10*$B$6 | D10: =$B$5-C10 | E10: =D10/$B$5 | F10: =D10/12
A12: Compare to the original uncapped-monthly worst case, which lost $46 on a single activation with no annual floor. Capping to 4/year turns the same worst-case experience selection into a comfortably profitable annual contract.

Sheet Recommended Tier 2 (Annual)
A1: Recommended — Tier 2: $275/mo Billed Monthly, Capped at 1 Multi-Experience Build-Out Per Year
A2: Same $275/mo price the member sees. Includes ONE combined build-out (up to 3 experiences, same date) per year. Additional build-outs billed a la carte at the member discount rate below.
A4: Monthly Price (as marketed) | B4: ='Tier 2 Profitability'!$B$3
A5: Annual Revenue (12 months, required commitment) | B5: =B4*12
A6: Annual Build-Out Cap (included) | B6: =Assumptions!$B$16
A8: Scenario | B8: Cost Per Build-Out | C8: Total Annual Cost (cap x cost) | D8: Annual Margin $ | E8: Annual Margin % | F8: Monthly-Equivalent Margin
A9: Worst case — 3 most expensive attended experiences combined | B9: =LARGE('Cost Per Experience'!K5:K15,1)+LARGE('Cost Per Experience'!K5:K15,2)+LARGE('Cost Per Experience'!K5:K15,3)+Assumptions!$B$8 | C9: =B9*$B$6 | D9: =$B$5-C9 | E9: =D9/$B$5 | F9: =D9/12
A10: Floor case — 3 cheapest non-attended experiences combined | B10: =SMALL('Cost Per Experience'!K16:K21,1)+SMALL('Cost Per Experience'!K16:K21,2)+SMALL('Cost Per Experience'!K16:K21,3)+Assumptions!$B$8 | C10: =B10*$B$6 | D10: =$B$5-C10 | E10: =D10/$B$5 | F10: =D10/12
A12: Additional build-outs beyond the included 1/year — suggested member rate
A13: Member discount vs. standard a la carte full build-out ($2,000+) | B13: 0.15 | C13: Editable. Extra build-outs still carry real margin since they're priced off your existing $2,000+ one-off rate, not the subscription rate.
A14: Suggested price for each additional build-out | B14: =2000*(1-B13)
A16: Compare to the original uncapped-monthly worst case, which lost $380 on a single combined event with no annual floor. Capping the included build-out to 1/year turns even the worst-case experience mix into a profitable annual contract, while extra build-outs stay priced near your existing high-margin one-off corporate rate.

Sheet Recommended vs Original
A1: Original (Uncapped Monthly) vs. Recommended (Annual-Capped) Structure
A2: Same headline prices members see ($199/mo, $275/mo). Only the usage cap changes. Worst-case experience selection used throughout for an apples-to-apples, conservative comparison.
B4: Original — Worst Case Monthly Margin | C4: Recommended — Worst Case Monthly-Equivalent Margin | D4: Improvement
A5: Tier 1 ($199/mo) | B5: ='Tier 1 Profitability'!$B$3-'Tier 1 Profitability'!$B$7 | C5: ='Recommended Tier 1 (Annual)'!F10 | D5: =C5-B5
A6: Tier 2 ($275/mo) | B6: ='Tier 2 Profitability'!$B$3-'Tier 2 Profitability'!$B$6 | C6: ='Recommended Tier 2 (Annual)'!F10 | D6: =C6-B6
A9: Bottom line: the price points you proposed ($199 / $275) work fine as marketing numbers. The failure mode in the original design was letting 'monthly' mean 'as often as they want, every month' with no ceiling on which experience they pick. Capping Tier 1 to quarterly use and Tier 2 to one annual build-out (with paid add-ons beyond that) fixes the margin at both tiers without changing the price a prospect sees.
